[{"name":"HTML","path":"api/categories/HTML.json","slug":"HTML","count":1},{"name":"CSS样式表","path":"api/categories/CSS样式表.json","slug":"CSS样式表","count":1},{"name":"Linux","path":"api/categories/Linux.json","slug":"Linux","count":4},{"name":"Python","path":"api/categories/Python.json","slug":"Python","count":2},{"name":"JavaScript","path":"api/categories/JavaScript.json","slug":"JavaScript","count":1},{"name":"Django","path":"api/categories/Django.json","slug":"Django","count":5},{"name":"基于urllib的基础爬虫","path":"api/categories/基于urllib的基础爬虫.json","slug":"基于urllib的基础爬虫","count":1}]